aethernet/__init__.py
aethernet-0.1.0.dist-info/METADATA
aethernet-0.1.0.dist-info/WHEEL
aethernet-0.1.0.dist-info/licenses/LICENSE-APACHE
aethernet-0.1.0.dist-info/licenses/LICENSE-MIT
aethernet-0.1.0.dist-info/RECORD
