Metadata-Version: 2.4
Name: aethernet
Version: 0.1.0
Summary: Redis based IPC
Author-email: Matt Campbell <matt@farixembedded.com>
License-Expression: MIT OR Apache-2.0
License-File: LICENSE-APACHE
License-File: LICENSE-MIT
Requires-Python: >=3.7
